{
    "watches": [
        {
            "PutRequest": {
                "Item": {
                    "bracelet_material": {
                        "S": "LEATHER ALLIGATOR"
                    },
                    "case_form": {
                        "S": "ROUND"
                    },
                    "case_material": {
                        "S": "STEEL"
                    },
                    "dial_color": {
                        "S": "BLACK"
                    },
                    "dial_material": {
                        "S": "STANDARD"
                    },
                    "gender": {
                        "S": "man"
                    },
                    "movement": {
                        "S": "CALIBRE_16_AUTO"
                    },
                    "sku": {
                        "S": "CV2A1P.FC6301"
                    },
                    "status": {
                        "S": "old"
                    },
                    "type": {
                        "S": "chrono"
                    },
                    "year": {
                        "N": "2013"
                    }
                }
            }
        },
        {
            "PutRequest": {
                "Item": {
                    "bracelet_material": {
                        "S": "STEEL"
                    },
                    "case_form": {
                        "S": "Round"
                    },
                    "case_material": {
                        "S": "STEEL"
                    },
                    "dial_color": {
                        "S": "BLACK"
                    },
                    "dial_material": {
                        "S": "STANDARD"
                    },
                    "gender": {
                        "S": "man"
                    },
                    "movement": {
                        "S": "Calibre 16 Day-Date"
                    },
                    "sku": {
                        "S": "CV2A1R.BA0799"
                    },
                    "status": {
                        "S": "current"
                    },
                    "type": {
                        "S": "chrono"
                    },
                    "year": {
                        "N": "2015"
                    }
                }
            }
        },
        {
            "PutRequest": {
                "Item": {
                    "bracelet_material": {
                        "S": "WITHOUT BRACELET"
                    },
                    "case_form": {
                        "S": "ROUND"
                    },
                    "case_material": {
                        "S": "STEEL"
                    },
                    "dial_color": {
                        "S": "BLACK"
                    },
                    "dial_material": {
                        "S": "STANDARD"
                    },
                    "gender": {
                        "S": "man"
                    },
                    "movement": {
                        "S": "CALIBRE_16_AUTO"
                    },
                    "sku": {
                        "S": "CV2A1R.CI6235"
                    },
                    "status": {
                        "S": "current"
                    },
                    "type": {
                        "S": "chrono"
                    },
                    "year": {
                        "N": "2015"
                    }
                }
            }
        },
        {
            "PutRequest": {
                "Item": {
                    "bracelet_material": {
                        "S": "LEATHER ALLIGATOR"
                    },
                    "case_form": {
                        "S": "Round"
                    },
                    "case_material": {
                        "S": "STEEL"
                    },
                    "dial_color": {
                        "S": "BLACK"
                    },
                    "dial_material": {
                        "S": "STANDARD"
                    },
                    "gender": {
                        "S": "man"
                    },
                    "movement": {
                        "S": "Calibre 16 Day-Date"
                    },
                    "sku": {
                        "S": "CV2A1R.FC6235"
                    },
                    "status": {
                        "S": "current"
                    },
                    "type": {
                        "S": "chrono"
                    },
                    "year": {
                        "N": "2015"
                    }
                }
            }
        },
        {
            "PutRequest": {
                "Item": {
                    "bracelet_material": {
                        "S": "STEEL"
                    },
                    "case_form": {
                        "S": "Round"
                    },
                    "case_material": {
                        "S": "STEEL & CERAMIC"
                    },
                    "dial_color": {
                        "S": "BROWN"
                    },
                    "dial_material": {
                        "S": "STANDARD"
                    },
                    "gender": {
                        "S": "man"
                    },
                    "movement": {
                        "S": "Calibre 16 Day-Date"
                    },
                    "sku": {
                        "S": "CV2A1S.BA0799"
                    },
                    "status": {
                        "S": "current"
                    },
                    "type": {
                        "S": "chrono"
                    },
                    "year": {
                        "N": "2015"
                    }
                }
            }
        },
        {
            "PutRequest": {
                "Item": {
                    "bracelet_material": {
                        "S": "WITHOUT BRACELET"
                    },
                    "case_form": {
                        "S": "ROUND"
                    },
                    "case_material": {
                        "S": "STEEL & CERAMIC"
                    },
                    "dial_color": {
                        "S": "BROWN"
                    },
                    "dial_material": {
                        "S": "STANDARD"
                    },
                    "gender": {
                        "S": "man"
                    },
                    "movement": {
                        "S": "CALIBRE_16_AUTO"
                    },
                    "sku": {
                        "S": "CV2A1S.CI6236"
                    },
                    "status": {
                        "S": "current"
                    },
                    "type": {
                        "S": "chrono"
                    },
                    "year": {
                        "N": "2015"
                    }
                }
            }
        },
        {
            "PutRequest": {
                "Item": {
                    "bracelet_material": {
                        "S": "LEATHER ALLIGATOR"
                    },
                    "case_form": {
                        "S": "Round"
                    },
                    "case_material": {
                        "S": "STEEL & CERAMIC"
                    },
                    "dial_color": {
                        "S": "BROWN"
                    },
                    "dial_material": {
                        "S": "STANDARD"
                    },
                    "gender": {
                        "S": "man"
                    },
                    "movement": {
                        "S": "Calibre 16 Day-Date"
                    },
                    "sku": {
                        "S": "CV2A1S.FC6236"
                    },
                    "status": {
                        "S": "current"
                    },
                    "type": {
                        "S": "chrono"
                    },
                    "year": {
                        "N": "2015"
                    }
                }
            }
        },
        {
            "PutRequest": {
                "Item": {
                    "bracelet_material": {
                        "S": "LEATHER"
                    },
                    "case_form": {
                        "S": "ROUND"
                    },
                    "case_material": {
                        "S": "STEEL & CERAMIC"
                    },
                    "dial_color": {
                        "S": "BROWN"
                    },
                    "dial_material": {
                        "S": "STANDARD"
                    },
                    "gender": {
                        "S": "man"
                    },
                    "movement": {
                        "S": "CALIBRE_16_AUTO"
                    },
                    "sku": {
                        "S": "CV2A1S.FCZ304"
                    },
                    "status": {
                        "S": "current"
                    },
                    "type": {
                        "S": "chrono"
                    },
                    "year": {
                        "N": "2017"
                    }
                }
            }
        },
        {
            "PutRequest": {
                "Item": {
                    "bracelet_material": {
                        "S": "STEEL"
                    },
                    "case_form": {
                        "S": "ROUND"
                    },
                    "case_material": {
                        "S": "STEEL"
                    },
                    "dial_color": {
                        "S": "BLACK"
                    },
                    "dial_material": {
                        "S": "STANDARD"
                    },
                    "gender": {
                        "S": "man"
                    },
                    "movement": {
                        "S": "CALIBRE_16_AUTO"
                    },
                    "sku": {
                        "S": "CV2A1T.BA0738"
                    },
                    "status": {
                        "S": "current"
                    },
                    "type": {
                        "S": "chrono"
                    },
                    "year": {
                        "N": "2017"
                    }
                }
            }
        },
        {
            "PutRequest": {
                "Item": {
                    "bracelet_material": {
                        "S": "STEEL"
                    },
                    "case_form": {
                        "S": "Round"
                    },
                    "case_material": {
                        "S": "STEEL & CERAMIC"
                    },
                    "dial_color": {
                        "S": "GREY"
                    },
                    "dial_material": {
                        "S": "STANDARD"
                    },
                    "gender": {
                        "S": "man"
                    },
                    "movement": {
                        "S": "Calibre 16"
                    },
                    "sku": {
                        "S": "CV2A1U.BA0738"
                    },
                    "status": {
                        "S": "current"
                    },
                    "type": {
                        "S": "chrono"
                    },
                    "year": {
                        "N": "2017"
                    }
                }
            }
        },
        {
            "PutRequest": {
                "Item": {
                    "bracelet_material": {
                        "S": "STEEL"
                    },
                    "case_form": {
                        "S": "Round"
                    },
                    "case_material": {
                        "S": "STEEL & CERAMIC"
                    },
                    "dial_color": {
                        "S": "BLUE"
                    },
                    "dial_material": {
                        "S": "STANDARD"
                    },
                    "gender": {
                        "S": "man"
                    },
                    "movement": {
                        "S": "Calibre 16"
                    },
                    "sku": {
                        "S": "CV2A1V.BA0738"
                    },
                    "status": {
                        "S": "current"
                    },
                    "type": {
                        "S": "chrono"
                    },
                    "year": {
                        "N": "2017"
                    }
                }
            }
        },
        {
            "PutRequest": {
                "Item": {
                    "bracelet_material": {
                        "S": "LEATHER"
                    },
                    "case_form": {
                        "S": "ROUND"
                    },
                    "case_material": {
                        "S": "TITANIUM"
                    },
                    "dial_color": {
                        "S": "BLACK"
                    },
                    "dial_material": {
                        "S": "STANDARD"
                    },
                    "gender": {
                        "S": "man"
                    },
                    "movement": {
                        "S": "CALIBRE_16_AUTO"
                    },
                    "sku": {
                        "S": "CV2A80.FC6256"
                    },
                    "status": {
                        "S": "old"
                    },
                    "type": {
                        "S": "chrono"
                    },
                    "year": {
                        "N": "2009"
                    }
                }
            }
        },
        {
            "PutRequest": {
                "Item": {
                    "bracelet_material": {
                        "S": "WITHOUT BRACELET"
                    },
                    "case_form": {
                        "S": "ROUND"
                    },
                    "case_material": {
                        "S": "TITANIUM"
                    },
                    "dial_color": {
                        "S": "BLACK"
                    },
                    "dial_material": {
                        "S": "STANDARD"
                    },
                    "gender": {
                        "S": "man"
                    },
                    "movement": {
                        "S": "CALIBRE_16_AUTO"
                    },
                    "sku": {
                        "S": "CV2A81.CI6237"
                    },
                    "status": {
                        "S": "current"
                    },
                    "type": {
                        "S": "chrono"
                    },
                    "year": {
                        "N": "2015"
                    }
                }
            }
        },
        {
            "PutRequest": {
                "Item": {
                    "bracelet_material": {
                        "S": "LEATHER ALLIGATOR"
                    },
                    "case_form": {
                        "S": "Round"
                    },
                    "case_material": {
                        "S": "TITANIUM"
                    },
                    "dial_color": {
                        "S": "BLACK"
                    },
                    "dial_material": {
                        "S": "STANDARD"
                    },
                    "gender": {
                        "S": "man"
                    },
                    "movement": {
                        "S": "Calibre 16 Day-Date"
                    },
                    "sku": {
                        "S": "CV2A81.FC6237"
                    },
                    "status": {
                        "S": "current"
                    },
                    "type": {
                        "S": "chrono"
                    },
                    "year": {
                        "N": "2015"
                    }
                }
            }
        },
        {
            "PutRequest": {
                "Item": {
                    "bracelet_material": {
                        "S": "WITHOUT BRACELET"
                    },
                    "case_form": {
                        "S": "ROUND"
                    },
                    "case_material": {
                        "S": "TITANIUM"
                    },
                    "dial_color": {
                        "S": "BLACK"
                    },
                    "dial_material": {
                        "S": "STANDARD"
                    },
                    "gender": {
                        "S": "man"
                    },
                    "movement": {
                        "S": "CALIBRE_16_AUTO"
                    },
                    "sku": {
                        "S": "CV2A82.CI6237"
                    },
                    "status": {
                        "S": "old"
                    },
                    "type": {
                        "S": "chrono"
                    },
                    "year": {
                        "N": "2015"
                    }
                }
            }
        },
        {
            "PutRequest": {
                "Item": {
                    "bracelet_material": {
                        "S": "LEATHER ALLIGATOR"
                    },
                    "case_form": {
                        "S": "ROUND"
                    },
                    "case_material": {
                        "S": "TITANIUM"
                    },
                    "dial_color": {
                        "S": "BLACK"
                    },
                    "dial_material": {
                        "S": "STANDARD"
                    },
                    "gender": {
                        "S": "man"
                    },
                    "movement": {
                        "S": "CALIBRE_16_AUTO"
                    },
                    "sku": {
                        "S": "CV2A82.FC6237"
                    },
                    "status": {
                        "S": "old"
                    },
                    "type": {
                        "S": "chrono"
                    },
                    "year": {
                        "N": "2015"
                    }
                }
            }
        },
        {
            "PutRequest": {
                "Item": {
                    "bracelet_material": {
                        "S": "WITHOUT BRACELET"
                    },
                    "case_form": {
                        "S": "ROUND"
                    },
                    "case_material": {
                        "S": "TITANIUM"
                    },
                    "dial_color": {
                        "S": "BLACK"
                    },
                    "dial_material": {
                        "S": "STANDARD"
                    },
                    "gender": {
                        "S": "man"
                    },
                    "movement": {
                        "S": "CALIBRE_16_AUTO"
                    },
                    "sku": {
                        "S": "CV2A83.CI6393"
                    },
                    "status": {
                        "S": "current"
                    },
                    "type": {
                        "S": "chrono"
                    },
                    "year": {
                        "N": "2016"
                    }
                }
            }
        },
        {
            "PutRequest": {
                "Item": {
                    "bracelet_material": {
                        "S": "LEATHER ALLIGATOR"
                    },
                    "case_form": {
                        "S": "ROUND"
                    },
                    "case_material": {
                        "S": "TITANIUM"
                    },
                    "dial_color": {
                        "S": "BLACK"
                    },
                    "dial_material": {
                        "S": "STANDARD"
                    },
                    "gender": {
                        "S": "man"
                    },
                    "movement": {
                        "S": "CALIBRE_16_AUTO"
                    },
                    "sku": {
                        "S": "CV2A83.FC6393"
                    },
                    "status": {
                        "S": "current"
                    },
                    "type": {
                        "S": "chrono"
                    },
                    "year": {
                        "N": "2016"
                    }
                }
            }
        },
        {
            "PutRequest": {
                "Item": {
                    "bracelet_material": {
                        "S": "LEATHER"
                    },
                    "case_form": {
                        "S": "Round"
                    },
                    "case_material": {
                        "S": "TITANIUM"
                    },
                    "dial_color": {
                        "S": "BLACK"
                    },
                    "dial_material": {
                        "S": "STANDARD"
                    },
                    "gender": {
                        "S": "man"
                    },
                    "movement": {
                        "S": "Calibre 16"
                    },
                    "sku": {
                        "S": "CV2A84.FC6394"
                    },
                    "status": {
                        "S": "current"
                    },
                    "type": {
                        "S": "chrono"
                    },
                    "year": {
                        "N": "2017"
                    }
                }
            }
        },
        {
            "PutRequest": {
                "Item": {
                    "bracelet_material": {
                        "S": "LEATHER ALLIGATOR"
                    },
                    "case_form": {
                        "S": "ROUND"
                    },
                    "case_material": {
                        "S": "STEEL"
                    },
                    "dial_color": {
                        "S": "BLACK"
                    },
                    "dial_material": {
                        "S": "STANDARD"
                    },
                    "gender": {
                        "S": "man"
                    },
                    "movement": {
                        "S": "CALIBRE_360"
                    },
                    "sku": {
                        "S": "CV5011.FC6191"
                    },
                    "status": {
                        "S": "old"
                    },
                    "type": {
                        "S": "chrono"
                    },
                    "year": {
                        "N": "2007"
                    }
                }
            }
        },
        {
            "PutRequest": {
                "Item": {
                    "bracelet_material": {
                        "S": "WITHOUT BRACELET"
                    },
                    "case_form": {
                        "S": "ROUND"
                    },
                    "case_material": {
                        "S": "STEEL"
                    },
                    "dial_color": {
                        "S": "BLACK"
                    },
                    "dial_material": {
                        "S": "STANDARD"
                    },
                    "gender": {
                        "S": "man"
                    },
                    "movement": {
                        "S": "CALIBRE_360"
                    },
                    "sku": {
                        "S": "CV5013.CI6232"
                    },
                    "status": {
                        "S": "old"
                    },
                    "type": {
                        "S": "chrono"
                    },
                    "year": {
                        "N": "2007"
                    }
                }
            }
        },
        {
            "PutRequest": {
                "Item": {
                    "bracelet_material": {
                        "S": "WITHOUT BRACELET"
                    },
                    "case_form": {
                        "S": "ROUND"
                    },
                    "case_material": {
                        "S": "GOLD"
                    },
                    "dial_color": {
                        "S": "GREY"
                    },
                    "dial_material": {
                        "S": "STANDARD"
                    },
                    "gender": {
                        "S": "man"
                    },
                    "movement": {
                        "S": "CALIBRE_360"
                    },
                    "sku": {
                        "S": "CV5040.CI8160"
                    },
                    "status": {
                        "S": "old"
                    },
                    "type": {
                        "S": "chrono"
                    },
                    "year": {
                        "N": "2005"
                    }
                }
            }
        },
        {
            "PutRequest": {
                "Item": {
                    "bracelet_material": {
                        "S": "LEATHER ALLIGATOR"
                    },
                    "case_form": {
                        "S": "ROUND"
                    },
                    "case_material": {
                        "S": "GOLD"
                    },
                    "dial_color": {
                        "S": "GREY"
                    },
                    "dial_material": {
                        "S": "STANDARD"
                    },
                    "gender": {
                        "S": "man"
                    },
                    "movement": {
                        "S": "CALIBRE_360"
                    },
                    "sku": {
                        "S": "CV5040.FC8160"
                    },
                    "status": {
                        "S": "old"
                    },
                    "type": {
                        "S": "chrono"
                    },
                    "year": {
                        "N": "2006"
                    }
                }
            }
        },
        {
            "PutRequest": {
                "Item": {
                    "bracelet_material": {
                        "S": "WITHOUT BRACELET"
                    },
                    "case_form": {
                        "S": "ROUND"
                    },
                    "case_material": {
                        "S": "GOLD"
                    },
                    "dial_color": {
                        "S": "BROWN"
                    },
                    "dial_material": {
                        "S": "STANDARD"
                    },
                    "gender": {
                        "S": "man"
                    },
                    "movement": {
                        "S": "CALIBRE_360"
                    },
                    "sku": {
                        "S": "CV5041.CI8164"
                    },
                    "status": {
                        "S": "old"
                    },
                    "type": {
                        "S": "chrono"
                    },
                    "year": {
                        "N": "2006"
                    }
                }
            }
        },
        {
            "PutRequest": {
                "Item": {
                    "bracelet_material": {
                        "S": "LEATHER ALLIGATOR"
                    },
                    "case_form": {
                        "S": "ROUND"
                    },
                    "case_material": {
                        "S": "GOLD"
                    },
                    "dial_color": {
                        "S": "BROWN"
                    },
                    "dial_material": {
                        "S": "STANDARD"
                    },
                    "gender": {
                        "S": "man"
                    },
                    "movement": {
                        "S": "CALIBRE_360"
                    },
                    "sku": {
                        "S": "CV5041.FC8164"
                    },
                    "status": {
                        "S": "old"
                    },
                    "type": {
                        "S": "chrono"
                    },
                    "year": {
                        "N": "2006"
                    }
                }
            }
        }
    ]
}