{
    "watches": [
        {
            "PutRequest": {
                "Item": {
                    "bracelet_material": {
                        "S": "STEEL"
                    },
                    "case_form": {
                        "S": "ROUND"
                    },
                    "case_material": {
                        "S": "STEEL"
                    },
                    "dial_color": {
                        "S": "BLACK"
                    },
                    "dial_material": {
                        "S": "STANDARD"
                    },
                    "gender": {
                        "S": "man"
                    },
                    "movement": {
                        "S": "MVT_QUARTZ"
                    },
                    "sku": {
                        "S": "WAU1114.BA0858"
                    },
                    "status": {
                        "S": "old"
                    },
                    "type": {
                        "S": "watch"
                    },
                    "year": {
                        "N": "2012"
                    }
                }
            }
        },
        {
            "PutRequest": {
                "Item": {
                    "bracelet_material": {
                        "S": "RUBBER"
                    },
                    "case_form": {
                        "S": "ROUND"
                    },
                    "case_material": {
                        "S": "STEEL"
                    },
                    "dial_color": {
                        "S": "BLACK"
                    },
                    "dial_material": {
                        "S": "STANDARD"
                    },
                    "gender": {
                        "S": "man"
                    },
                    "movement": {
                        "S": "MVT_QUARTZ"
                    },
                    "sku": {
                        "S": "WAU1115.FT6024"
                    },
                    "status": {
                        "S": "old"
                    },
                    "type": {
                        "S": "watch"
                    },
                    "year": {
                        "N": "2012"
                    }
                }
            }
        },
        {
            "PutRequest": {
                "Item": {
                    "bracelet_material": {
                        "S": "STEEL"
                    },
                    "case_form": {
                        "S": "ROUND"
                    },
                    "case_material": {
                        "S": "STEEL"
                    },
                    "dial_color": {
                        "S": "GREY"
                    },
                    "dial_material": {
                        "S": "STANDARD"
                    },
                    "gender": {
                        "S": "man"
                    },
                    "movement": {
                        "S": "MVT_QUARTZ"
                    },
                    "sku": {
                        "S": "WAU1117.BA0858"
                    },
                    "status": {
                        "S": "old"
                    },
                    "type": {
                        "S": "watch"
                    },
                    "year": {
                        "N": "2013"
                    }
                }
            }
        },
        {
            "PutRequest": {
                "Item": {
                    "bracelet_material": {
                        "S": "STEEL"
                    },
                    "case_form": {
                        "S": "ROUND"
                    },
                    "case_material": {
                        "S": "STEEL"
                    },
                    "dial_color": {
                        "S": "BLACK"
                    },
                    "dial_material": {
                        "S": "STANDARD"
                    },
                    "gender": {
                        "S": "man"
                    },
                    "movement": {
                        "S": "MVT_QUARTZ"
                    },
                    "sku": {
                        "S": "WAU111A.BA0858"
                    },
                    "status": {
                        "S": "old"
                    },
                    "type": {
                        "S": "watch"
                    },
                    "year": {
                        "N": "2012"
                    }
                }
            }
        },
        {
            "PutRequest": {
                "Item": {
                    "bracelet_material": {
                        "S": "STEEL"
                    },
                    "case_form": {
                        "S": "ROUND"
                    },
                    "case_material": {
                        "S": "STEEL"
                    },
                    "dial_color": {
                        "S": "WHITE"
                    },
                    "dial_material": {
                        "S": "STANDARD"
                    },
                    "gender": {
                        "S": "man"
                    },
                    "movement": {
                        "S": "MVT_QUARTZ"
                    },
                    "sku": {
                        "S": "WAU111B.BA0858"
                    },
                    "status": {
                        "S": "old"
                    },
                    "type": {
                        "S": "watch"
                    },
                    "year": {
                        "N": "2012"
                    }
                }
            }
        },
        {
            "PutRequest": {
                "Item": {
                    "bracelet_material": {
                        "S": "STEEL & CERAMIC"
                    },
                    "case_form": {
                        "S": "ROUND"
                    },
                    "case_material": {
                        "S": "STEEL & CERAMIC"
                    },
                    "dial_color": {
                        "S": "GREY"
                    },
                    "dial_material": {
                        "S": "STANDARD"
                    },
                    "gender": {
                        "S": "man"
                    },
                    "movement": {
                        "S": "MVT_QUARTZ"
                    },
                    "sku": {
                        "S": "WAU111C.BA0869"
                    },
                    "status": {
                        "S": "old"
                    },
                    "type": {
                        "S": "watch"
                    },
                    "year": {
                        "N": "2013"
                    }
                }
            }
        },
        {
            "PutRequest": {
                "Item": {
                    "bracelet_material": {
                        "S": "RUBBER"
                    },
                    "case_form": {
                        "S": "ROUND"
                    },
                    "case_material": {
                        "S": "STEEL & CERAMIC"
                    },
                    "dial_color": {
                        "S": "GREY"
                    },
                    "dial_material": {
                        "S": "STANDARD"
                    },
                    "gender": {
                        "S": "man"
                    },
                    "movement": {
                        "S": "MVT_QUARTZ"
                    },
                    "sku": {
                        "S": "WAU111D.FT6024"
                    },
                    "status": {
                        "S": "old"
                    },
                    "type": {
                        "S": "watch"
                    },
                    "year": {
                        "N": "2013"
                    }
                }
            }
        },
        {
            "PutRequest": {
                "Item": {
                    "bracelet_material": {
                        "S": "STEEL & CERAMIC"
                    },
                    "case_form": {
                        "S": "ROUND"
                    },
                    "case_material": {
                        "S": "STEEL & CERAMIC"
                    },
                    "dial_color": {
                        "S": "BLACK"
                    },
                    "dial_material": {
                        "S": "STANDARD"
                    },
                    "gender": {
                        "S": "woman"
                    },
                    "movement": {
                        "S": "CALIBRE_5_AUTO"
                    },
                    "sku": {
                        "S": "WAU2210.BA0859"
                    },
                    "status": {
                        "S": "old"
                    },
                    "type": {
                        "S": "watch"
                    },
                    "year": {
                        "N": "2012"
                    }
                }
            }
        },
        {
            "PutRequest": {
                "Item": {
                    "bracelet_material": {
                        "S": "STEEL & CERAMIC"
                    },
                    "case_form": {
                        "S": "ROUND"
                    },
                    "case_material": {
                        "S": "STEEL & CERAMIC"
                    },
                    "dial_color": {
                        "S": "WHITE"
                    },
                    "dial_material": {
                        "S": "STANDARD"
                    },
                    "gender": {
                        "S": "woman"
                    },
                    "movement": {
                        "S": "CALIBRE_5_AUTO"
                    },
                    "sku": {
                        "S": "WAU2211.BA0861"
                    },
                    "status": {
                        "S": "old"
                    },
                    "type": {
                        "S": "watch"
                    },
                    "year": {
                        "N": "2012"
                    }
                }
            }
        },
        {
            "PutRequest": {
                "Item": {
                    "bracelet_material": {
                        "S": "STEEL & CERAMIC"
                    },
                    "case_form": {
                        "S": "ROUND"
                    },
                    "case_material": {
                        "S": "STEEL & CERAMIC"
                    },
                    "dial_color": {
                        "S": "BLACK"
                    },
                    "dial_material": {
                        "S": "STANDARD"
                    },
                    "gender": {
                        "S": "woman"
                    },
                    "movement": {
                        "S": "CALIBRE_5_AUTO"
                    },
                    "sku": {
                        "S": "WAU2212.BA0859"
                    },
                    "status": {
                        "S": "old"
                    },
                    "type": {
                        "S": "watch"
                    },
                    "year": {
                        "N": "2012"
                    }
                }
            }
        },
        {
            "PutRequest": {
                "Item": {
                    "bracelet_material": {
                        "S": "STEEL & CERAMIC"
                    },
                    "case_form": {
                        "S": "Round"
                    },
                    "case_material": {
                        "S": "STEEL & CERAMIC"
                    },
                    "dial_color": {
                        "S": "WHITE"
                    },
                    "dial_material": {
                        "S": "STANDARD"
                    },
                    "gender": {
                        "S": "woman"
                    },
                    "movement": {
                        "S": "CALIBRE_5_AUTO"
                    },
                    "sku": {
                        "S": "WAU2213.BA0861"
                    },
                    "status": {
                        "S": "old"
                    },
                    "type": {
                        "S": "watch"
                    },
                    "year": {
                        "N": "2012"
                    }
                }
            }
        },
        {
            "PutRequest": {
                "Item": {
                    "bracelet_material": {
                        "S": "STEEL"
                    },
                    "case_form": {
                        "S": "ROUND"
                    },
                    "case_material": {
                        "S": "STEEL"
                    },
                    "dial_color": {
                        "S": "BLACK"
                    },
                    "dial_material": {
                        "S": "STANDARD"
                    },
                    "gender": {
                        "S": "man"
                    },
                    "movement": {
                        "S": "CALIBRE_8_CHRM"
                    },
                    "sku": {
                        "S": "WAV5111.BA0901"
                    },
                    "status": {
                        "S": "old"
                    },
                    "type": {
                        "S": "watch"
                    },
                    "year": {
                        "N": "2007"
                    }
                }
            }
        },
        {
            "PutRequest": {
                "Item": {
                    "bracelet_material": {
                        "S": "WITHOUT BRACELET"
                    },
                    "case_form": {
                        "S": "ROUND"
                    },
                    "case_material": {
                        "S": "STEEL"
                    },
                    "dial_color": {
                        "S": "BLACK"
                    },
                    "dial_material": {
                        "S": "STANDARD"
                    },
                    "gender": {
                        "S": "man"
                    },
                    "movement": {
                        "S": "CALIBRE_8_CHRM"
                    },
                    "sku": {
                        "S": "WAV5111.CI6225"
                    },
                    "status": {
                        "S": "old"
                    },
                    "type": {
                        "S": "watch"
                    },
                    "year": {
                        "N": "2007"
                    }
                }
            }
        },
        {
            "PutRequest": {
                "Item": {
                    "bracelet_material": {
                        "S": "LEATHER ALLIGATOR"
                    },
                    "case_form": {
                        "S": "ROUND"
                    },
                    "case_material": {
                        "S": "STEEL"
                    },
                    "dial_color": {
                        "S": "BLACK"
                    },
                    "dial_material": {
                        "S": "STANDARD"
                    },
                    "gender": {
                        "S": "man"
                    },
                    "movement": {
                        "S": "CALIBRE_8_CHRM"
                    },
                    "sku": {
                        "S": "WAV5111.FC6225"
                    },
                    "status": {
                        "S": "old"
                    },
                    "type": {
                        "S": "watch"
                    },
                    "year": {
                        "N": "2007"
                    }
                }
            }
        },
        {
            "PutRequest": {
                "Item": {
                    "bracelet_material": {
                        "S": "STEEL"
                    },
                    "case_form": {
                        "S": "ROUND"
                    },
                    "case_material": {
                        "S": "STEEL"
                    },
                    "dial_color": {
                        "S": "GREY"
                    },
                    "dial_material": {
                        "S": "STANDARD"
                    },
                    "gender": {
                        "S": "man"
                    },
                    "movement": {
                        "S": "CALIBRE_8_CHRM"
                    },
                    "sku": {
                        "S": "WAV5112.BA0901"
                    },
                    "status": {
                        "S": "old"
                    },
                    "type": {
                        "S": "watch"
                    },
                    "year": {
                        "N": "2007"
                    }
                }
            }
        },
        {
            "PutRequest": {
                "Item": {
                    "bracelet_material": {
                        "S": "WITHOUT BRACELET"
                    },
                    "case_form": {
                        "S": "ROUND"
                    },
                    "case_material": {
                        "S": "STEEL"
                    },
                    "dial_color": {
                        "S": "GREY"
                    },
                    "dial_material": {
                        "S": "STANDARD"
                    },
                    "gender": {
                        "S": "man"
                    },
                    "movement": {
                        "S": "CALIBRE_8_CHRM"
                    },
                    "sku": {
                        "S": "WAV5112.CI6225"
                    },
                    "status": {
                        "S": "old"
                    },
                    "type": {
                        "S": "watch"
                    },
                    "year": {
                        "N": "2007"
                    }
                }
            }
        },
        {
            "PutRequest": {
                "Item": {
                    "bracelet_material": {
                        "S": "WITHOUT BRACELET"
                    },
                    "case_form": {
                        "S": "ROUND"
                    },
                    "case_material": {
                        "S": "STEEL"
                    },
                    "dial_color": {
                        "S": "GREY"
                    },
                    "dial_material": {
                        "S": "STANDARD"
                    },
                    "gender": {
                        "S": "man"
                    },
                    "movement": {
                        "S": "CALIBRE_8_CHRM"
                    },
                    "sku": {
                        "S": "WAV5112.CI6231"
                    },
                    "status": {
                        "S": "old"
                    },
                    "type": {
                        "S": "watch"
                    },
                    "year": {
                        "N": "2007"
                    }
                }
            }
        },
        {
            "PutRequest": {
                "Item": {
                    "bracelet_material": {
                        "S": "LEATHER ALLIGATOR"
                    },
                    "case_form": {
                        "S": "ROUND"
                    },
                    "case_material": {
                        "S": "STEEL"
                    },
                    "dial_color": {
                        "S": "GREY"
                    },
                    "dial_material": {
                        "S": "STANDARD"
                    },
                    "gender": {
                        "S": "man"
                    },
                    "movement": {
                        "S": "CALIBRE_8_CHRM"
                    },
                    "sku": {
                        "S": "WAV5112.FC6225"
                    },
                    "status": {
                        "S": "old"
                    },
                    "type": {
                        "S": "watch"
                    },
                    "year": {
                        "N": "2007"
                    }
                }
            }
        },
        {
            "PutRequest": {
                "Item": {
                    "bracelet_material": {
                        "S": "LEATHER ALLIGATOR"
                    },
                    "case_form": {
                        "S": "ROUND"
                    },
                    "case_material": {
                        "S": "STEEL"
                    },
                    "dial_color": {
                        "S": "GREY"
                    },
                    "dial_material": {
                        "S": "STANDARD"
                    },
                    "gender": {
                        "S": "man"
                    },
                    "movement": {
                        "S": "CALIBRE_8_CHRM"
                    },
                    "sku": {
                        "S": "WAV5112.FC6231"
                    },
                    "status": {
                        "S": "old"
                    },
                    "type": {
                        "S": "watch"
                    },
                    "year": {
                        "N": "2007"
                    }
                }
            }
        },
        {
            "PutRequest": {
                "Item": {
                    "bracelet_material": {
                        "S": "STEEL"
                    },
                    "case_form": {
                        "S": "ROUND"
                    },
                    "case_material": {
                        "S": "STEEL"
                    },
                    "dial_color": {
                        "S": "BROWN"
                    },
                    "dial_material": {
                        "S": "STANDARD"
                    },
                    "gender": {
                        "S": "man"
                    },
                    "movement": {
                        "S": "CALIBRE_8_CHRM"
                    },
                    "sku": {
                        "S": "WAV5113.BA0901"
                    },
                    "status": {
                        "S": "old"
                    },
                    "type": {
                        "S": "watch"
                    },
                    "year": {
                        "N": "2007"
                    }
                }
            }
        },
        {
            "PutRequest": {
                "Item": {
                    "bracelet_material": {
                        "S": "WITHOUT BRACELET"
                    },
                    "case_form": {
                        "S": "ROUND"
                    },
                    "case_material": {
                        "S": "STEEL"
                    },
                    "dial_color": {
                        "S": "BROWN"
                    },
                    "dial_material": {
                        "S": "STANDARD"
                    },
                    "gender": {
                        "S": "man"
                    },
                    "movement": {
                        "S": "CALIBRE_8_CHRM"
                    },
                    "sku": {
                        "S": "WAV5113.CI6231"
                    },
                    "status": {
                        "S": "old"
                    },
                    "type": {
                        "S": "watch"
                    },
                    "year": {
                        "N": "2007"
                    }
                }
            }
        },
        {
            "PutRequest": {
                "Item": {
                    "bracelet_material": {
                        "S": "LEATHER ALLIGATOR"
                    },
                    "case_form": {
                        "S": "ROUND"
                    },
                    "case_material": {
                        "S": "STEEL"
                    },
                    "dial_color": {
                        "S": "BROWN"
                    },
                    "dial_material": {
                        "S": "STANDARD"
                    },
                    "gender": {
                        "S": "man"
                    },
                    "movement": {
                        "S": "CALIBRE_8_CHRM"
                    },
                    "sku": {
                        "S": "WAV5113.FC6231"
                    },
                    "status": {
                        "S": "old"
                    },
                    "type": {
                        "S": "watch"
                    },
                    "year": {
                        "N": "2007"
                    }
                }
            }
        },
        {
            "PutRequest": {
                "Item": {
                    "bracelet_material": {
                        "S": "LEATHER ALLIGATOR"
                    },
                    "case_form": {
                        "S": "ROUND"
                    },
                    "case_material": {
                        "S": "STEEL"
                    },
                    "dial_color": {
                        "S": "BLACK"
                    },
                    "dial_material": {
                        "S": "STANDARD"
                    },
                    "gender": {
                        "S": "man"
                    },
                    "movement": {
                        "S": "CALIBRE_8_CHRM"
                    },
                    "sku": {
                        "S": "WAV5114.FC6238"
                    },
                    "status": {
                        "S": "old"
                    },
                    "type": {
                        "S": "watch"
                    },
                    "year": {
                        "N": "2008"
                    }
                }
            }
        },
        {
            "PutRequest": {
                "Item": {
                    "bracelet_material": {
                        "S": "STEEL"
                    },
                    "case_form": {
                        "S": "ROUND"
                    },
                    "case_material": {
                        "S": "STEEL"
                    },
                    "dial_color": {
                        "S": "BLACK"
                    },
                    "dial_material": {
                        "S": "STANDARD"
                    },
                    "gender": {
                        "S": "man"
                    },
                    "movement": {
                        "S": "CALIBRE_8_CHRM"
                    },
                    "sku": {
                        "S": "WAV5115.BA0901"
                    },
                    "status": {
                        "S": "old"
                    },
                    "type": {
                        "S": "watch"
                    },
                    "year": {
                        "N": "2008"
                    }
                }
            }
        },
        {
            "PutRequest": {
                "Item": {
                    "bracelet_material": {
                        "S": "WITHOUT BRACELET"
                    },
                    "case_form": {
                        "S": "ROUND"
                    },
                    "case_material": {
                        "S": "STEEL"
                    },
                    "dial_color": {
                        "S": "BLACK"
                    },
                    "dial_material": {
                        "S": "STANDARD"
                    },
                    "gender": {
                        "S": "man"
                    },
                    "movement": {
                        "S": "CALIBRE_8_CHRM"
                    },
                    "sku": {
                        "S": "WAV5115.CI6225"
                    },
                    "status": {
                        "S": "old"
                    },
                    "type": {
                        "S": "watch"
                    },
                    "year": {
                        "N": "2008"
                    }
                }
            }
        }
    ]
}